genjipk_sdk/__init__.py
genjipk_sdk/change_requests.py
genjipk_sdk/completions.py
genjipk_sdk/difficulties.py
genjipk_sdk/helpers.py
genjipk_sdk/internal.py
genjipk_sdk/logs.py
genjipk_sdk/lootbox.py
genjipk_sdk/maps.py
genjipk_sdk/newsfeed.py
genjipk_sdk/py.typed
genjipk_sdk/rank_card.py
genjipk_sdk/tags.py
genjipk_sdk/users.py
genjipk_sdk/xp.py
genjipk_sdk-2.5.0.dist-info/METADATA
genjipk_sdk-2.5.0.dist-info/WHEEL
genjipk_sdk-2.5.0.dist-info/RECORD
