Metadata-Version: 2.4
Name: genjipk-sdk
Version: 2.5.0
Summary: A command library for Genji Parkour services.
Author-email: tylovejoy <48333668+tylovejoy@users.noreply.github.com>
Requires-Python: >=3.13
Requires-Dist: msgspec>=0.19.0
